django_telegram_app/__init__.py
django_telegram_app/admin.py
django_telegram_app/apps.py
django_telegram_app/checks.py
django_telegram_app/conf.py
django_telegram_app/models.py
django_telegram_app/urls.py
django_telegram_app/views.py
django_telegram_app/bot/__init__.py
django_telegram_app/bot/base.py
django_telegram_app/bot/bot.py
django_telegram_app/bot/testing/__init__.py
django_telegram_app/bot/testing/testcases.py
django_telegram_app/locale/nl/LC_MESSAGES/django.po
django_telegram_app/management/__init__.py
django_telegram_app/management/base.py
django_telegram_app/management/commands/__init__.py
django_telegram_app/management/commands/setcommands.py
django_telegram_app/management/commands/setwebhook.py
django_telegram_app/migrations/0001_initial.py
django_telegram_app/migrations/0002_remove_telegramsettings_user.py
django_telegram_app/migrations/__init__.py
django_telegram_app-1.3.4.dist-info/licenses/LICENSE
django_telegram_app-1.3.4.dist-info/METADATA
django_telegram_app-1.3.4.dist-info/WHEEL
django_telegram_app-1.3.4.dist-info/top_level.txt
django_telegram_app-1.3.4.dist-info/RECORD
