Metadata-Version: 2.4
Name: django-telegram-app
Version: 1.3.4
Summary: A Django app that integrates with Telegram to create bots.
Author-email: Sonny Valkeneers <sonny@softllama.net>
License-Expression: MIT
Project-URL: Repository, https://github.com/shifqu/django-telegram-app.git
Project-URL: Issues, https://github.com/shifqu/django-telegram-app/issues
Project-URL: ReleaseNotes, https://github.com/shifqu/django-telegram-app/releases
Project-URL: Funding, https://github.com/sponsors/shifqu
Classifier: Environment :: Web Environment
Classifier: Framework :: Django
Classifier: Framework :: Django :: 5.2
Classifier: Intended Audience :: Developers
Classifier: Operating System :: OS Independent
Classifier: Programming Language :: Python
Classifier: Programming Language :: Python :: 3
Classifier: Programming Language :: Python :: 3 :: Only
Classifier: Programming Language :: Python :: 3.10
Classifier: Programming Language :: Python :: 3.11
Classifier: Programming Language :: Python :: 3.12
Classifier: Programming Language :: Python :: 3.13
Classifier: Programming Language :: Python :: 3.14
Classifier: Topic :: Internet
Classifier: Topic :: Communications :: Chat
Classifier: Topic :: Software Development :: Libraries :: Application Frameworks
Classifier: Topic :: Software Development :: Libraries :: Python Modules
Requires-Python: >=3.10
License-File: LICENSE
Requires-Dist: django>=5.2
Requires-Dist: requests>=2.32
Provides-Extra: dev
Requires-Dist: coverage>=7.11; extra == "dev"
Requires-Dist: django-types>=0.22; extra == "dev"
Requires-Dist: ruff>=0.14; extra == "dev"
Requires-Dist: pylint>=4.0; extra == "dev"
Requires-Dist: pyright>=1.1; extra == "dev"
Provides-Extra: build
Requires-Dist: build>=1.3; extra == "build"
Requires-Dist: twine>=6.2; extra == "build"
Dynamic: license-file
